rs_enums/__init__.py
rs_enums/generics.py
rs_enums/option.py
rs_enums/result.py
rs_enums-0.1.2b0.dist-info/LICENSE
rs_enums-0.1.2b0.dist-info/METADATA
rs_enums-0.1.2b0.dist-info/WHEEL
rs_enums-0.1.2b0.dist-info/RECORD
