Metadata-Version: 2.1
Name: rs-enums
Version: 0.1.2b0
Summary: rs_enums is a Python module inspired by Rust's powerful Option and Result enums.
License: Apache-2.0
Author: Kubanychbek uulu Kairat
Author-email: kubanychbekukairat@gmail.com
Requires-Python: >=3.11,<4.0
Classifier: License :: OSI Approved :: Apache Software License
Classifier: Programming Language :: Python :: 3
Classifier: Programming Language :: Python :: 3.11
Classifier: Programming Language :: Python :: 3.12
Classifier: Programming Language :: Python :: 3.13
Requires-Dist: pytest (>=8.3.0,<9.0.0)
